{"date":"2026-04-04","period_days":30,"overall":{"total_runs":98,"total_tokens":122587011,"total_cost":0,"total_action_minutes":806},"workflows":[{"workflow_name":"CI Cleaner","run_count":2,"total_tokens":22734152,"avg_tokens":11367076,"total_cost":0,"avg_cost":0.0,"total_turns":239,"avg_turns":119.5,"total_action_minutes":77,"error_count":0,"warning_count":0,"latest_run_id":"23984950167"},{"workflow_name":"Smoke Copilot","run_count":16,"total_tokens":20140468,"avg_tokens":1258779,"total_cost":0,"avg_cost":0.0,"total_turns":333,"avg_turns":20.8,"total_action_minutes":145,"error_count":2,"warning_count":0,"latest_run_id":"23987300615"},{"workflow_name":"Daily Community Attribution Updater","run_count":1,"total_tokens":12844407,"avg_tokens":12844407,"total_cost":0,"avg_cost":0.0,"total_turns":135,"avg_turns":135.0,"total_action_minutes":23,"error_count":0,"warning_count":0,"latest_run_id":"23977260451"},{"workflow_name":"Contribution Check","run_count":5,"total_tokens":11248952,"avg_tokens":2249790,"total_cost":0,"avg_cost":0.0,"total_turns":322,"avg_turns":64.4,"total_action_minutes":56,"error_count":3,"warning_count":0,"latest_run_id":"23987462980"},{"workflow_name":"Daily Syntax Error Quality Check","run_count":1,"total_tokens":9234988,"avg_tokens":9234988,"total_cost":0,"avg_cost":0.0,"total_turns":131,"avg_turns":131.0,"total_action_minutes":20,"error_count":0,"warning_count":0,"latest_run_id":"23977056913"},{"workflow_name":"Copilot CLI Deep Research Agent","run_count":1,"total_tokens":4229635,"avg_tokens":4229635,"total_cost":0,"avg_cost":0.0,"total_turns":53,"avg_turns":53.0,"total_action_minutes":14,"error_count":0,"warning_count":0,"latest_run_id":"23987484834"},{"workflow_name":"Daily Firewall Logs Collector and Reporter","run_count":1,"total_tokens":3854714,"avg_tokens":3854714,"total_cost":0,"avg_cost":0.0,"total_turns":38,"avg_turns":38.0,"total_action_minutes":22,"error_count":0,"warning_count":0,"latest_run_id":"23978151852"},{"workflow_name":"Auto-Triage Issues","run_count":8,"total_tokens":2996044,"avg_tokens":374506,"total_cost":0,"avg_cost":0.0,"total_turns":67,"avg_turns":8.4,"total_action_minutes":40,"error_count":0,"warning_count":0,"latest_run_id":"23986194803"},{"workflow_name":"Daily Testify Uber Super Expert","run_count":1,"total_tokens":2895202,"avg_tokens":2895202,"total_cost":0,"avg_cost":0.0,"total_turns":50,"avg_turns":50.0,"total_action_minutes":9,"error_count":0,"warning_count":0,"latest_run_id":"23977962300"},{"workflow_name":"Agent Container Smoke Test","run_count":17,"total_tokens":2560145,"avg_tokens":150597,"total_cost":0,"avg_cost":0.0,"total_turns":68,"avg_turns":4.0,"total_action_minutes":84,"error_count":1,"warning_count":0,"latest_run_id":"23988420654"},{"workflow_name":"Q","run_count":1,"total_tokens":2509556,"avg_tokens":2509556,"total_cost":0,"avg_cost":0.0,"total_turns":35,"avg_turns":35.0,"total_action_minutes":19,"error_count":1,"warning_count":0,"latest_run_id":"23973579905"},{"workflow_name":"Code Simplifier","run_count":1,"total_tokens":2490441,"avg_tokens":2490441,"total_cost":0,"avg_cost":0.0,"total_turns":46,"avg_turns":46.0,"total_action_minutes":12,"error_count":0,"warning_count":0,"latest_run_id":"23972687286"},{"workflow_name":"Workflow Health Manager - Meta-Orchestrator","run_count":1,"total_tokens":2431926,"avg_tokens":2431926,"total_cost":0,"avg_cost":0.0,"total_turns":35,"avg_turns":35.0,"total_action_minutes":11,"error_count":0,"warning_count":0,"latest_run_id":"23978397450"},{"workflow_name":"Dead Code Removal Agent","run_count":1,"total_tokens":2376283,"avg_tokens":2376283,"total_cost":0,"avg_cost":0.0,"total_turns":36,"avg_turns":36.0,"total_action_minutes":14,"error_count":0,"warning_count":0,"latest_run_id":"23978319418"},{"workflow_name":"Agent Performance Analyzer - Meta-Orchestrator","run_count":1,"total_tokens":2238379,"avg_tokens":2238379,"total_cost":0,"avg_cost":0.0,"total_turns":38,"avg_turns":38.0,"total_action_minutes":11,"error_count":0,"warning_count":0,"latest_run_id":"23971272196"},{"workflow_name":"Documentation Noob Tester","run_count":1,"total_tokens":2069415,"avg_tokens":2069415,"total_cost":0,"avg_cost":0.0,"total_turns":39,"avg_turns":39.0,"total_action_minutes":11,"error_count":0,"warning_count":0,"latest_run_id":"23979591960"},{"workflow_name":"PR Triage Agent","run_count":3,"total_tokens":1734790,"avg_tokens":578263,"total_cost":0,"avg_cost":0.0,"total_turns":39,"avg_turns":13.0,"total_action_minutes":21,"error_count":0,"warning_count":0,"latest_run_id":"23984798749"},{"workflow_name":"Delight","run_count":1,"total_tokens":1594776,"avg_tokens":1594776,"total_cost":0,"avg_cost":0.0,"total_turns":25,"avg_turns":25.0,"total_action_minutes":8,"error_count":0,"warning_count":0,"latest_run_id":"23978416349"},{"workflow_name":"Daily Malicious Code Scan Agent","run_count":1,"total_tokens":1503165,"avg_tokens":1503165,"total_cost":0,"avg_cost":0.0,"total_turns":32,"avg_turns":32.0,"total_action_minutes":6,"error_count":0,"warning_count":0,"latest_run_id":"23987763144"},{"workflow_name":"jsweep - JavaScript Unbloater","run_count":1,"total_tokens":1363492,"avg_tokens":1363492,"total_cost":0,"avg_cost":0.0,"total_turns":23,"avg_turns":23.0,"total_action_minutes":11,"error_count":1,"warning_count":0,"latest_run_id":"23971251326"}],"_trimmed":true,"_original_workflow_count":42}